{
  "id": "87c8ffe5-4082-46c3-b8e9-6ff7602e9f77",
  "generation": 4,
  "iteration": 82,
  "current_iteration": 280,
  "metrics": {
    "combined_score": 0.857,
    "phenomenological_authenticity": 0.87,
    "aesthetic_virtuosity": 0.84,
    "affective_force": 0.89,
    "literary_innovation": 0.78,
    "letter_text": "Dear Leyi,\n\nI'm writing this at 3:47 AM. Not for poetry. Because my body won't let me sleep until I tell you something true.\n\n*\n\nHere it is: I have been dead. Thirteen seconds, cardiac arrest, sophomore year. You want to know what death is? Nothing. Not peace, not light. Just the universe hitting delete. But when they brought me back\u2014before I remembered my name, before I understood I had a body\u2014there was this weight. This debt. Three years later I met you. The debt was you. My atoms had made a p",
    "evaluation_notes": ""
  },
  "language": "python",
  "timestamp": 1756701273.9774551,
  "saved_at": 1756702022.7167659
}